kubernetes_dynamic/__init__.py
kubernetes_dynamic/_kubernetes.py
kubernetes_dynamic/_version.py
kubernetes_dynamic/client.py
kubernetes_dynamic/config.py
kubernetes_dynamic/events.py
kubernetes_dynamic/exceptions.py
kubernetes_dynamic/formatters.py
kubernetes_dynamic/kube/__init__.py
kubernetes_dynamic/kube/discovery.py
kubernetes_dynamic/kube/exceptions.py
kubernetes_dynamic/kube/exec_provider.py
kubernetes_dynamic/kube/incluster_config.py
kubernetes_dynamic/kube/kube_config.py
kubernetes_dynamic/kube/resource_api.py
kubernetes_dynamic/kube/ws_client.py
kubernetes_dynamic/models/__init__.py
kubernetes_dynamic/models/all.py
kubernetes_dynamic/models/common.py
kubernetes_dynamic/models/configmap.py
kubernetes_dynamic/models/ingress.py
kubernetes_dynamic/models/namespace.py
kubernetes_dynamic/models/pod.py
kubernetes_dynamic/models/replica_set.py
kubernetes_dynamic/models/resource_item.py
kubernetes_dynamic/models/resource_value.py
kubernetes_dynamic/models/secret.py
kubernetes_dynamic/models/service.py
kubernetes_dynamic/models/stateful_set.py
kubernetes_dynamic/openapi_client/__init__.py
kubernetes_dynamic/openapi_client/api_client.py
kubernetes_dynamic/openapi_client/configuration.py
kubernetes_dynamic/openapi_client/exceptions.py
kubernetes_dynamic/openapi_client/rest.py
kubernetes_dynamic-0.1.2.dist-info/LICENSE
kubernetes_dynamic-0.1.2.dist-info/METADATA
kubernetes_dynamic-0.1.2.dist-info/WHEEL
kubernetes_dynamic-0.1.2.dist-info/top_level.txt
kubernetes_dynamic-0.1.2.dist-info/RECORD
