Metadata-Version: 2.1
Name: kubernetes-dynamic
Version: 0.1.2
Summary: Kubernetes Dynamic client
Author-email: Attila Kobor <atti92@gmail.com>, Balazs Hamorszky <balihb@gmail.com>
License: BSD-3-Clause
Project-URL: homepage, https://github.com/atti92/kubernetes-dynamic
Project-URL: documentation, https://github.com/atti92/kubernetes-dynamic
Project-URL: repository, https://github.com/atti92/kubernetes-dynamic.git
Project-URL: changelog, https://github.com/atti92/kubernetes-dynamic/blob/main/README.md
Keywords: kubernetes,client,kubernetes-client,kubernetes-dynamic,dynamic
Classifier: Development Status :: 4 - Beta
Classifier: Framework :: Pydantic
Classifier: Intended Audience :: Developers
Classifier: License :: Freely Distributable
Classifier: Programming Language :: Python :: 3
Requires-Python: >=3.7
License-File: LICENSE
Requires-Dist: pydantic (<2.0,>=1.10.0)
Requires-Dist: urllib3
Requires-Dist: requests-oauthlib
Requires-Dist: PyYAML
Requires-Dist: oauthlib
Requires-Dist: google-auth
Requires-Dist: websocket-client
Requires-Dist: certifi
Requires-Dist: python-dateutil
